tests/__init__.py
tests/utils.py
tests/common/__init__.py
tests/common/aggregation/__init__.py
tests/common/aggregation/test_anti_entropy.py
tests/common/gossip/__init__.py
tests/common/gossip/test_gossiping.py
tests/extreme/__init__.py
tests/extreme/clustering/__init__.py
tests/extreme/clustering/test_tman.py
tests/extreme/dissemination/__init__.py
tests/extreme/dissemination/lpbcast/__init__.py
tests/extreme/dissemination/lpbcast/test_lpbcast.py
tests/extreme/dissemination/mon/__init__.py
tests/extreme/dissemination/mon/test_mon.py
tests/extreme/membership/__init__.py
tests/extreme/membership/test_newscast.py
tests/extreme/sampling/__init__.py
tests/extreme/sampling/test_mrwb.py
tests/extreme/searching/__init__.py
tests/extreme/searching/test_k_walker.py
tests/stable/__init__.py
tests/stable/clustering/__init__.py
tests/stable/clustering/test_x_bot.py
tests/stable/dissemination/__init__.py
tests/stable/dissemination/test_brisa.py
tests/stable/dissemination/test_plumtree.py
tests/stable/membership/__init__.py
tests/stable/membership/test_hyparview.py
tests/stable/sampling/__init__.py
tests/stable/sampling/test_rwd.py
tests/stable/searching/__init__.py
tests/stable/searching/test_abloom.py
unsserv/__init__.py
unsserv/high_level_api.py
unsserv/common/__init__.py
unsserv/common/errors.py
unsserv/common/services_abc.py
unsserv/common/structs.py
unsserv/common/typing.py
unsserv/common/utils.py
unsserv/common/aggregation/__init__.py
unsserv/common/aggregation/anti_entropy.py
unsserv/common/aggregation/config.py
unsserv/common/gossip/__init__.py
unsserv/common/gossip/config.py
unsserv/common/gossip/gossip.py
unsserv/common/gossip/protocol.py
unsserv/common/gossip/structs.py
unsserv/common/gossip/typing.py
unsserv/common/rpc/__init__.py
unsserv/common/rpc/protocol.py
unsserv/common/rpc/rpc.py
unsserv/common/rpc/structs.py
unsserv/extreme/__init__.py
unsserv/extreme/aggregation/__init__.py
unsserv/extreme/aggregation/anti_entropy.py
unsserv/extreme/clustering/__init__.py
unsserv-0.0.5.dist-info/LICENSE
unsserv-0.0.5.dist-info/METADATA
unsserv-0.0.5.dist-info/WHEEL
unsserv-0.0.5.dist-info/top_level.txt
unsserv-0.0.5.dist-info/RECORD
