Metadata-Version: 2.1
Name: unsserv
Version: 0.0.5
Summary: P2P out-of-the-box high-level library
Home-page: https://github.com/aratz-lasa/py-unsserv
Author: Aratz M. Lasa
Author-email: aratz.m.lasa@gmail.com
License: UNKNOWN
Project-URL: Documentation, https://py-unsserv.readthedocs.io/en/latest/
Project-URL: Source Code, https://github.com/aratz-lasa/py-unsserv
Keywords: unsserv p2p unstructured membership network clustering bias aggregation sampling search dissemination broadcast pubsub
Platform: UNKNOWN
Classifier: Programming Language :: Python :: 3
Classifier: License :: OSI Approved :: MIT License
Classifier: Operating System :: OS Independent
Requires-Python: >=3.7
Requires-Dist: rpcudp (==4.0.0)
Provides-Extra: dev
Requires-Dist: pytest (==5.4.1) ; extra == 'dev'
Requires-Dist: pytest-asyncio (==0.11.0) ; extra == 'dev'
Requires-Dist: mypy (==0.740) ; extra == 'dev'
Requires-Dist: flake8 (==3.7.9) ; extra == 'dev'
Requires-Dist: black (==19.10b0) ; extra == 'dev'
